modules/ramDmaCi/ramDmaCi.v

module ramDmaCi #(parameter[7:0] customId = 8'h00)
                (input wire start,
                            clock,
                            reset,
                input wire [31:0] valueA,
                                    valueB,
                input wire [ 7 : 0 ] ciN,
                output wire [31:0] result,
                output wire done);

 // declare an array of 32 bit words of depth 512

reg [31:0] ram [511:0];

reg started;
reg almost_done;

 integer i;


reg [31:0] data_out;
reg reading;
reg [7:0] address;

always @(posedge clock)
begin
    
  if (reset)
  begin
    started <= 0;
    reading <= 0;

    data_out <= 0;
    almost_done <= 0;
    for (i = 0; i < 512; i =i+1)
    begin
        ram[i] <= 0;
    end
  end
  else
    begin
        if (start)
        begin
        started = 1;
        end
        if (reading)
        begin
            data_out <= ram[address];
            almost_done = 1;
            reading <= 0;
        end
        else
        if (started & (ciN == customId) & (valueA[31:9] == 0))
        begin
           //we check if 9th bit is 1 or 0
            if (valueA[8] == 1'b1)
            begin
                //if 9th bit is 1, we write valueB to ram[valueA[31:10]]
                //address is from 31 to 10 including
                ram[valueA[7:0]] = valueB;
                almost_done = 1;
    
            end
            else
            begin
                //if 9th bit is 0, we read value from ram and write it to result
                almost_done = 0;
                address = valueA[7:0];
                reading = 1;
            end
        end
        
    end
  
end

assign done = almost_done;
assign result = data_out;

endmodule

modules/ramDmaCi/tb_ramDmaCi.v
`timescale 1ps/1ps
module ramDmaCiTestBench;

/* set the time-units for simulation */



  reg reset, clock;
  initial 
    begin
      reset = 1'b1;
      clock = 1'b0;                 /* set the initial values */
      repeat (4) #5 clock = ~clock; /* generate 2 clock periods */
      reset = 1'b0;                 /* de-activate the reset */
      forever #5 clock = ~clock;    /* generate a clock with a period of 10 time-units */
    end
  
 
    reg start;
    reg [31:0] valueA;
    reg [31:0] valueB;
    reg [7:0] customId;
    reg [7:0] ciN;

    ramDmaCi #(8'h01 ) DUT
         (.clock(clock),
          .reset(reset),
          .start(start),
          .valueA(valueA),
          .valueB(valueB),
          
          .ciN(ciN));
  
  initial
    begin
      $dumpfile("fifoSignals.vcd"); /* define the name of the .vcd file that can be viewed by GTKWAVE */
      $dumpvars(1,DUT);             /* dump all signals inside the DUT-component in the .vcd file */
    end

  initial
    begin

        start = 1'b0;
        valueA = 32'd0;
        valueB = 32'd0;

        @(negedge reset);            /* wait for the reset period to end */
        repeat(2) @(negedge clock);  /* wait for 2 clock cycles */
        start = 1'b1;
        valueA = 32'h100;
        valueB = 32'hFF;
        ciN = 8'd1;
        repeat(1) @(negedge clock);

        valueA = 32'h000;
        valueB = 32'h00;
        ciN = 8'd0;

        repeat(1) @(negedge clock);

        ciN = 8'd1;

        valueA = 32'h000;
        valueB = 32'h00;
        repeat(1) @(negedge clock);

        ciN = 8'd0;

        valueA = 32'h000;
        valueB = 32'h00;

        repeat(1) @(negedge clock);
        








      
      $finish;                     /* finish the simulation */
    end

endmodule

fifoSignals.vcd
$date
	Tue Apr 16 14:27:26 2024
$end
$version
	Icarus Verilog
$end
$timescale
	1ps
$end
$scope module ramDmaCiTestBench $end
$scope module DUT $end
$var wire 8 ! ciN [7:0] $end
$var wire 1 " clock $end
$var wire 1 # done $end
$var wire 1 $ reset $end
$var wire 32 % result [31:0] $end
$var wire 1 & start $end
$var wire 32 ' valueA [31:0] $end
$var wire 32 ( valueB [31:0] $end
$var reg 8 ) address [7:0] $end
$var reg 1 * almost_done $end
$var reg 32 + data_out [31:0] $end
$var reg 1 , reading $end
$var reg 1 - started $end
$var integer 32 . i [31:0] $end
$upscope $end
$upscope $end
$enddefinitions $end
#0
$dumpvars
bx .
x-
x,
bx +
x*
bx )
b0 (
b0 '
0&
bx %
1$
x#
0"
bx !
$end
#5
0#
0*
b0 %
b0 +
0,
0-
b1000000000 .
1"
#10
0"
#15
b1000000000 .
1"
#20
0$
0"
#25
1"
#30
0"
#35
1"
#40
b1 !
b11111111 (
b100000000 '
1&
0"
#45
1#
1*
1-
1"
#50
b0 !
b0 (
b0 '
0"
#55
1"
#60
b1 !
0"
#65
1,
b0 )
0#
0*
1"
#70
b0 !
0"
#75
b11111111 %
b11111111 +
1#
1*
1"
