modules/ramDmaCi/dualPortSSRAM.v
module dualPortSSRAM #( parameter bitwidth = 8,
                        parameter nrOfEntries = 512)
                      ( input wire                             clock,
                                                               writeEnableA, writeEnableB,
                        input wire [$clog2(nrOfEntries)-1 : 0] addressA, addressB,
                        input wire [bitwidth-1 : 0]            dataInA, dataInB,
                        output reg [bitwidth-1 : 0]            dataOutA, dataOutB);
  
  reg [bitwidth-1 : 0] memoryContent [nrOfEntries-1 : 0];
  
  always @(posedge clock)
    begin
      if (writeEnableA == 1'b1) memoryContent[addressA] = dataInA;
      dataOutA = memoryContent[addressA];
    end

  always @(negedge clock)
    begin
      if (writeEnableB == 1'b1) memoryContent[addressB] = dataInB;
      dataOutB = memoryContent[addressB];
    end

endmodule

modules/ramDmaCi/ramDmaCi.v
// code adapted using trial and error from modules/delay/verilog/delayIse.v
module ramDmaCi #(  parameter [7:0] customInstructionId = 8'd0 )
                ( input wire         clock,
                                     reset,
                                     ciStart,
                  input wire [7:0]   ciN,
                  input wire [31:0]  ciValueA,
                                     ciValueB,
                  output wire        ciDone,
                  output wire [31:0] ciResult,
                  
                  // here the bus interface is defined
                  output wire        requestTransaction,
                  input wire         transactionGranted,

                  //we still need to read some of the signals
                  input wire         beginTransactionIn,
                                     endTransactionIn,
                                     readNotWriteIn,
                                     dataValidIn,
                                     busErrorIn,
                                     busyIn,
                  input wire [31:0]  addressDataIn,
                  input wire [3:0]   byteEnablesIn,
                  input wire [7:0]   burstSizeIn,

                  //we are the masters, we set the signals
                  output reg         readNotWriteOut,
                                     startTransactionOutReg,
                                     endTransactionReg,
                                     beginTransactionOut,
                                     dataValidOutReg,
                  output reg [3:0]   byteEnablesOut,
                  output reg [7:0]   burstSizeOut,
                  output wire [31:0] addressDataOut);

    //cpu interface
    localparam [21:0] OP_MEM = 22'b000, OP_BUS_SA = 22'b001, OP_MEM_SA = 22'b010, OP_BLOCK_SIZE = 22'b011, OP_BURST_SIZE = 22'b100, OP_CONTROL = 22'b101;

    wire isMyCi = (ciN == customInstructionId) ? ciStart : 1'b0;

    //memory and operation
    wire [21:0] memoryOp = ciValueA[31:10];
    wire writeEnableCPU = ciValueA[9];
    wire writeEnableA = writeEnableCPU & isMyCi & (memoryOp == 22'b000);
    wire [31:0] dataOutA;
    wire [8:0] addressCPU = ciValueA[8:0];


    //dma related functionality
    reg [31:0] busStartAddress;
    reg [8:0] memoryStartAddress; //refers to the inner memory of this instruction, not the FPGA's ram
    reg [9:0] blockSize;
    reg [7:0] burstSize;
    reg [1:0] status;
    reg doWrite;

    //write values to operation registers
    always @ (posedge clock) begin

      if (reset) begin
        busStartAddress <= 32'b0;
        memoryStartAddress = 9'b0;
        blockSize = 10'b0;
        burstSize = 8'b0;
        doWrite = 1'b0;
      end else if (isMyCi & writeEnableCPU) begin
        busStartAddress <= (memoryOp == OP_BUS_SA) ? ciValueB : busStartAddress;
        memoryStartAddress <= (memoryOp == OP_MEM_SA) ? ciValueB[8:0] : memoryStartAddress;
        blockSize <= (memoryOp == OP_BLOCK_SIZE) ? ciValueB[9:0] : blockSize;
        burstSize <= (memoryOp == OP_BURST_SIZE) ? ciValueB[7:0] : burstSize;
        doWrite <=  (memoryOp != OP_CONTROL) ? doWrite :
                    (ciValueB[0] == 1'b1) ? 1'b0 :
                    (ciValueB[1] == 1'b1) ? 1'b1 : 1'b0;
                    
                
      end
    end

    wire        bufferWe;
    wire [8:0]  bufferAddress;
    wire [31:0] bufferDataIn;
    wire [31:0] bufferDataOut;

    // instatiate the dualPortSSRAM module
    dualPortSSRAM #(.bitwidth(32), .nrOfEntries(512)) ssram 
                    (.clock(clock), .writeEnableA(writeEnableA), .writeEnableB(bufferWe), 
                    .addressA(addressCPU), .addressB(bufferAddress), .dataInA(ciValueB), .dataInB(bufferDataIn), 
                    .dataOutA(dataOutA), .dataOutB(bufferDataOut));
    

    //read values from operation registers
    reg [31:0] dataOutCPU;
    always @*
    case (memoryOp)
      OP_MEM: dataOutCPU = dataOutA;
      OP_BUS_SA: dataOutCPU = busStartAddress;
      OP_MEM_SA: dataOutCPU = memoryStartAddress;
      OP_BLOCK_SIZE: dataOutCPU = blockSize;
      OP_BURST_SIZE: dataOutCPU = burstSize;
      OP_CONTROL: dataOutCPU = status;
      default: dataOutCPU = 32'hEEEEEEEE;
    endcase
    
    wire validReadOp = (memoryOp == OP_MEM || memoryOp == OP_BUS_SA || memoryOp == OP_MEM_SA || memoryOp == OP_BLOCK_SIZE || memoryOp == OP_BURST_SIZE || memoryOp == OP_CONTROL) & ~writeEnableCPU & isMyCi;
  /*
   *
   * Here we define the main counter, needed for multiple CC operation
   *
   */
    reg s_doneReg;
    reg [31:0] s_delayCountReg;
    wire s_delayCountZero = (s_delayCountReg == 32'd0) ? 1'd1 : 1'd0;
    wire s_delayCountOne  = (s_delayCountReg == 32'd1) ? 1'd1 : 1'd0;
    wire [31:0] s_delayCountNext = (reset == 1'b1) ? 32'd0 :
                                    (validReadOp) ? 32'd1:
                                    (s_delayCountZero == 1'b0) ? s_delayCountReg - 32'd1 : s_delayCountReg;

  /*
   *
   * Here we define the done signal
   *
   */

    assign ciResult = (s_doneReg == 1'b1) ? dataOutCPU : 32'd0;
    wire s_doneNext = ((isMyCi == 1'b1 && ciValueA == 32'd0) || //this valueA here won't be 0 like ever,
                                                                //but if you remove the line it stalls the cpu
                       (s_delayCountOne == 1'b1)) ? 1'b1 : 1'b0;
  
    assign ciDone = s_doneReg | (isMyCi == 1'b1 && writeEnableCPU);
  
    always @(posedge clock)
    begin
      s_delayCountReg <= s_delayCountNext;
      s_doneReg <= s_doneNext;
    end

  /*
   *
   * Here the bus interface is defined
   *
   */
    localparam [3:0] IDLE = 4'd0, REQUEST = 4'd1, INIT = 4'd2, COMPUTE_BURSTSIZE = 4'd3, READ = 4'd4, ERROR = 4'd6, WRITE = 4'd7, WRITE_DONE_OK = 4'd8, WRITE_DONE_ERR = 4'd9;
    reg [31:0] s_busAddressInReg;
    reg [31:0] s_busAddressReg;
    reg [31:0] s_busDataInReg, s_busDataOutReg;
    reg s_transactionActiveReg, s_busDataInValidReg;
    reg s_endTransactionInReg;

    reg [3:0] s_dmaState, s_dmaStateNext;

    always @ (posedge clock)
    begin
        s_busDataInReg          <= (dataValidIn == 1'b1) ? addressDataIn : s_busDataInReg;
        s_busDataInValidReg     <= dataValidIn;
        s_endTransactionInReg   <= endTransactionIn & ~reset;

    end
  /*
   *
   * Here the dma-controller is defined, adapted from modules/hdmi_720p/verilog/graphicsController.v
   *
   */

  reg [8:0] s_bufferAddressReg;
  reg [7:0] nextBurstSize, burstCountReg;
  reg [9:0] remainingBlockSize;

  wire s_startTransfer = isMyCi & writeEnableCPU & (memoryOp == OP_CONTROL) & (s_dmaState == IDLE) & (ciValueB[0] ^ ciValueB[1]);

  //assign endTransactionOut   = s_endTransactionReg;
  //assign dataValidOut        = s_dataValidOutReg;
  assign addressDataOut      = s_busDataOutReg;
  //assign beginTransactionOut = s_startTransactionOutReg;
  assign requestTransaction = (s_dmaState == REQUEST) ? 1'd1 : 1'd0;
  assign bufferDataIn       = s_busDataInReg;
  assign bufferAddress      = s_bufferAddressReg;
  assign bufferWe           = (s_dmaState == READ) ? s_busDataInValidReg : 1'd0;
  //assign writeIndex         = s_writeIndexReg;

  //state machine description
  always @*
    case (s_dmaState)
      IDLE             : s_dmaStateNext <= (s_startTransfer == 1'b1) ? COMPUTE_BURSTSIZE : IDLE;
      COMPUTE_BURSTSIZE: s_dmaStateNext <= (remainingBlockSize != 9'b0) ? REQUEST : IDLE;
      REQUEST          : s_dmaStateNext <= (transactionGranted == 1'b1) ? INIT : REQUEST;
      INIT             : s_dmaStateNext <= doWrite ? WRITE : READ;
      READ             : s_dmaStateNext <= (busErrorIn == 1'b1 && endTransactionIn == 1'b0) ? ERROR :
                                           (busErrorIn == 1'b1) ? IDLE : 
                                           (s_endTransactionInReg == 1'b1) ? COMPUTE_BURSTSIZE : READ;
      WRITE            : s_dmaStateNext <= (busErrorIn == 1'b1) ? WRITE_DONE_ERR : 
                                           (burstCountReg[7] == 1'b1 && (busyIn == 1'b0)) ? WRITE_DONE_OK : WRITE;
      WRITE_DONE_OK    : s_dmaStateNext <= COMPUTE_BURSTSIZE;
      ERROR            : s_dmaStateNext <= (s_endTransactionInReg == 1'b1) ? IDLE : ERROR;
      default          : s_dmaStateNext <= IDLE;
    endcase
  
  //advance state machine
  always @(posedge clock)
    begin
      //s_writeIndexReg          <= (reset == 1'd1) ? 1'b0 : (s_dmaState == READ_DONE || (s_dmaState == WRITE_BLACK && s_writeAddressReg[9] == 1'b1)) ? ~s_writeIndexReg : s_writeIndexReg;
      s_dmaState               <= (reset == 1'd1) ? IDLE : s_dmaStateNext;
      remainingBlockSize       <= (reset == 1'd1) ? 10'd0 :
                                  (s_startTransfer == 1'd1) ? blockSize :
                                  (s_dmaState != COMPUTE_BURSTSIZE) ? remainingBlockSize :
                                  (remainingBlockSize > burstSize) ? remainingBlockSize - burstSize - 1 : 10'd0;
      nextBurstSize            <= (reset == 1'd1) ? 8'd0 :
                                  (s_dmaState != COMPUTE_BURSTSIZE) ? nextBurstSize :
                                  (remainingBlockSize > burstSize) ? burstSize : remainingBlockSize[7:0];
      burstCountReg            <= (s_dmaState == COMPUTE_BURSTSIZE) ? nextBurstSize - 8'd1 :
                                  ((s_dmaState == WRITE)) ? burstCountReg - 8'd1 : burstCountReg;
      s_bufferAddressReg       <= (reset == 1'd1) ? 9'd0 :
                                  (s_startTransfer == 1'b1) ? memoryStartAddress :
                                  ((s_dmaState == READ) && s_busDataInValidReg == 1'd1) ? s_bufferAddressReg + 9'd1 : 
                                  ((s_dmaState == WRITE) && (busyIn == 1'b0)) ? s_bufferAddressReg + 9'd1 : s_bufferAddressReg;
      s_busAddressReg          <= (reset == 1'b1) ? 32'd0 :
                                  (s_startTransfer == 1'b1) ? {busStartAddress[31:2], 2'b0} :
                                  (s_busDataInValidReg == 1'b1 && (s_dmaState == READ)) ? s_busAddressReg + 32'd4 :
                                  ((s_dmaState == WRITE) && (busyIn == 1'b0)) ? s_busAddressReg + 32'd4 : s_busAddressReg;
      s_busDataOutReg          <= (s_dmaState == INIT) ? s_busAddressReg :
                                  (s_dmaState == WRITE) ? bufferDataOut : 32'd0;
      beginTransactionOut    <= (s_dmaState == INIT) ? 1'b1 : 1'b0;
      dataValidOutReg          <= (s_dmaState == WRITE) ? 1'b1 : 1'b0;
      endTransactionReg        <= ((s_dmaState == WRITE_DONE_OK) || (s_dmaState == WRITE_DONE_ERR)) ? 1'b1 : 1'b0;
      byteEnablesOut           <= (s_dmaState == INIT) ? 4'hF : 4'd0;
      readNotWriteOut          <= ((s_dmaState == INIT) && ~doWrite) ? 1'b1 : 1'b0;
      burstSizeOut             <= (s_dmaState == INIT) ? nextBurstSize : 8'd0;
      startTransactionOutReg   <= (s_dmaState == INIT) ? 1'b1 : 1'b0;
      status[0]                <= ((s_dmaState == INIT) || (s_dmaState == READ) || (s_dmaState == WRITE) || (s_dmaState == COMPUTE_BURSTSIZE)) ? 1'b1 : 1'b0;
      status[1]                <= (s_dmaState == INIT) ? 1'b0 :
                                  (s_dmaState == ERROR) ? 1'b1 : status[1];
    end
endmodule

modules/ramDmaCi/tb_controller.v
module tb_dmaController;

    // Parameters
    localparam CLOCK_PERIOD = 10; // Clock period in simulation time units

    // Signals
    reg clock = 0;
    reg reset = 0;
    reg start = 0;

    reg bus_error = 0;
    reg [31:0] valueA;
    reg [31:0] valueB;
    reg [7:0] ciN = 0;
    wire [31:0] result;
    wire done;
    wire request;
    wire end_transaction;
    reg slave_busy =0;
    wire begin_transaction;
    reg bus_aquire =0;
    wire in_valid;
    reg end_transaction_reg =0;
    reg data_valid =1;

    // Instantiate the DMA Controller
    ramDmaCi #(8'd12 ) DUT  (.clock(clock),
          .reset(reset),
          .ciStart(start),
          .ciN(ciN),
          .ciValueA(valueA),
          .ciValueB(valueB),
          .ciDone(done),
          .ciResult(),
          .requestTransaction(request),
          .transactionGranted(bus_aquire),
          .beginTransactionIn(),
          .endTransactionIn(end_transaction_reg),
          .readNotWriteIn(),
          .dataValidIn(data_valid),
          .addressDataIn(),
          .busyIn(1'b0),
          .byteEnablesIn(),
          .burstSizeIn(),
          .readNotWriteOut(),
          .busErrorIn(bus_error),
          .startTransactionOutReg(),
          .burstSizeOut(),
          .addressDataOut(),
          .byteEnablesOut(),
          .endTransactionReg(),
          .burstSizeOut()
          );


    initial
        begin
          $dumpfile("fifoSignals.vcd"); /* define the name of the .vcd file that can be viewed by GTKWAVE */
          $dumpvars(1,DUT);             /* dump all signals inside the DUT-component in the .vcd file */
        end

    // Clock generation
    always #((CLOCK_PERIOD / 2)) clock = ~clock;

    // Test stimulus
    initial begin
        // Reset the DMA controller
        reset = 1;
        #10;
        reset = 0;

        //test case 1 set block size to 1
        start = 1;
        ciN = 8'd12;
        #10


        valueA = 32'hE00;
        valueB = 32'h15;

        #10
        //burst size 5

        valueA = 32'h1200;
        valueB = 32'h5;


        
        $display("memOp: %d", valueA[31:10]);

        #10
        //set control_reg to 2
        valueA = 32'h1700;
        valueB = 32'h2;
        #10
        valueA = 32'h000;
        valueB = 32'h0;
        bus_aquire = 1;
        #10
        start = 0;

       

        // Finish simulation
        #300;
        $finish;
    end

endmodule

fifoSignals.vcd
$date
	Mon Apr 29 21:29:56 2024
$end
$version
	Icarus Verilog
$end
$timescale
	1s
$end
$scope module tb_dmaController $end
$scope module DUT $end
$var wire 32 ! addressDataIn [31:0] $end
$var wire 32 " addressDataOut [31:0] $end
$var wire 1 # beginTransactionIn $end
$var wire 9 $ bufferAddress [8:0] $end
$var wire 32 % bufferDataIn [31:0] $end
$var wire 8 & burstSizeIn [7:0] $end
$var wire 1 ' busErrorIn $end
$var wire 1 ( busyIn $end
$var wire 4 ) byteEnablesIn [3:0] $end
$var wire 1 * ciDone $end
$var wire 8 + ciN [7:0] $end
$var wire 1 , ciStart $end
$var wire 32 - ciValueA [31:0] $end
$var wire 32 . ciValueB [31:0] $end
$var wire 1 / clock $end
$var wire 1 0 dataValidIn $end
$var wire 1 1 endTransactionIn $end
$var wire 1 2 readNotWriteIn $end
$var wire 1 3 reset $end
$var wire 1 4 s_startTransfer $end
$var wire 1 5 transactionGranted $end
$var wire 1 6 validReadOp $end
$var wire 1 7 writeEnableA $end
$var wire 1 8 writeEnableCPU $end
$var wire 1 9 s_doneNext $end
$var wire 1 : s_delayCountZero $end
$var wire 1 ; s_delayCountOne $end
$var wire 32 < s_delayCountNext [31:0] $end
$var wire 1 = requestTransaction $end
$var wire 22 > memoryOp [21:0] $end
$var wire 1 ? isMyCi $end
$var wire 32 @ dataOutA [31:0] $end
$var wire 32 A ciResult [31:0] $end
$var wire 1 B bufferWe $end
$var wire 32 C bufferDataOut [31:0] $end
$var wire 9 D addressCPU [8:0] $end
$var reg 1 E beginTransactionOut $end
$var reg 10 F blockSize [9:0] $end
$var reg 8 G burstCountReg [7:0] $end
$var reg 8 H burstSize [7:0] $end
$var reg 8 I burstSizeOut [7:0] $end
$var reg 32 J busStartAddress [31:0] $end
$var reg 4 K byteEnablesOut [3:0] $end
$var reg 32 L dataOutCPU [31:0] $end
$var reg 1 M dataValidOutReg $end
$var reg 1 N doWrite $end
$var reg 1 O endTransactionReg $end
$var reg 9 P memoryStartAddress [8:0] $end
$var reg 8 Q nextBurstSize [7:0] $end
$var reg 1 R readNotWriteOut $end
$var reg 10 S remainingBlockSize [9:0] $end
$var reg 9 T s_bufferAddressReg [8:0] $end
$var reg 32 U s_busAddressReg [31:0] $end
$var reg 32 V s_busDataInReg [31:0] $end
$var reg 1 W s_busDataInValidReg $end
$var reg 32 X s_busDataOutReg [31:0] $end
$var reg 32 Y s_delayCountReg [31:0] $end
$var reg 4 Z s_dmaState [3:0] $end
$var reg 4 [ s_dmaStateNext [3:0] $end
$var reg 1 \ s_doneReg $end
$var reg 1 ] s_endTransactionInReg $end
$var reg 1 ^ startTransactionOutReg $end
$var reg 2 _ status [1:0] $end
$upscope $end
$upscope $end
$enddefinitions $end
#0
$dumpvars
bx _
x^
x]
x\
b0 [
bx Z
bx Y
bx X
xW
bx V
bx U
bx T
bx S
xR
bx Q
bx P
xO
xN
xM
bx L
bx K
bx J
bx I
bx H
bx G
bx F
xE
bx D
bx C
xB
bx A
bx @
0?
bx >
x=
b0 <
x;
x:
x9
x8
07
06
05
04
13
z2
01
10
0/
bx .
bx -
0,
b0 +
x*
bz )
0(
0'
bz &
bx %
bx $
z#
bx "
bz !
$end
#5
09
1:
0;
0=
0B
b0 J
b0 Y
0]
1W
bz %
bz V
b0 U
b0 $
b0 T
b0 Q
b0 S
b0 Z
bx0xxx0xxx0xxx0xxx0xxx0xxx0xxx0 A
b11101110111011101110111011101110 L
0N
b0 H
b0 F
b0 P
1/
#10
b0xx [
x4
x9
b0x <
x7
x6
1?
0/
b1100 +
1,
03
#15
b0 [
bx <
x=
x:
x;
bx0 _
0^
b0 I
0R
b0 K
0O
0M
0E
b0 "
b0 X
b0xx Z
b0x Y
1/
#20
06
04
b0 A
1*
07
b0 L
b11 >
18
b0 D
0/
b10101 .
b111000000000 -
#25
b0x0x0x A
b10101 L
0=
b10101 F
bx Y
bx _
x^
xR
bx K
xE
b0 Z
1/
#30
b0 A
b0 L
b100 >
0/
b101 .
b1001000000000 -
#35
b0x0x A
b101 L
bx0 _
0^
0R
b0 K
0E
b101 H
1/
#40
b11 [
14
b0x0 A
b0x0 L
b101 >
b100000000 D
0/
b10 .
b1011100000000 -
#45
b1 [
04
1N
b10101 S
b11 Z
1/
#50
b1 <
16
bx A
x*
19
bx L
b0 >
08
b0 D
0/
15
b0 .
b0 -
#55
b10 [
1=
1*
0:
1;
bx1 _
b11111111 G
b101 Q
b1111 S
b1 Z
1\
b1 Y
1/
#60
b0 <
06
0?
0/
0,
#65
b111 [
09
b0 <
1:
0;
0=
b0 Y
bx0 _
b10 Z
1/
#70
0/
#75
b1000 [
b0 A
0*
b1 _
1^
b101 I
b1111 K
1E
b111 Z
0\
1/
#80
0/
#85
b11 [
0^
b0 I
b0 K
1M
0E
bx "
bx X
b100 U
b1 $
b1 T
b11111110 G
b1000 Z
1/
#90
0/
#95
b1 [
b0 _
1O
0M
b0 "
b0 X
b11 Z
1/
#100
0/
#105
b10 [
1=
b1 _
0O
b100 G
b1001 S
b1 Z
1/
#110
0/
#115
b111 [
0=
b0 _
b10 Z
1/
#120
0/
#125
b1 _
1^
b101 I
b1111 K
1E
b100 "
b100 X
b111 Z
1/
#130
0/
#135
0^
b0 I
b0 K
1M
0E
bx "
bx X
b1000 U
b10 $
b10 T
b11 G
1/
#140
0/
#145
b1100 U
b11 $
b11 T
b10 G
1/
#150
0/
#155
b10000 U
b100 $
b100 T
b1 G
1/
#160
0/
#165
b10100 U
b101 $
b101 T
b0 G
1/
#170
0/
#175
b1000 [
b11000 U
b110 $
b110 T
b11111111 G
1/
#180
0/
#185
b11 [
b11100 U
b111 $
b111 T
b11111110 G
b1000 Z
1/
#190
0/
#195
b1 [
b0 _
1O
0M
b0 "
b0 X
b11 Z
1/
#200
0/
#205
b10 [
1=
b1 _
0O
b100 G
b11 S
b1 Z
1/
#210
0/
#215
b111 [
0=
b0 _
b10 Z
1/
#220
0/
#225
b1 _
1^
b101 I
b1111 K
1E
b11100 "
b11100 X
b111 Z
1/
#230
0/
#235
0^
b0 I
b0 K
1M
0E
bx "
bx X
b100000 U
b1000 $
b1000 T
b11 G
1/
#240
0/
#245
b100100 U
b1001 $
b1001 T
b10 G
1/
#250
0/
#255
b101000 U
b1010 $
b1010 T
b1 G
1/
#260
0/
#265
b101100 U
b1011 $
b1011 T
b0 G
1/
#270
0/
#275
b1000 [
b110000 U
b1100 $
b1100 T
b11111111 G
1/
#280
0/
#285
b11 [
b110100 U
b1101 $
b1101 T
b11111110 G
b1000 Z
1/
#290
0/
#295
b1 [
b0 _
1O
0M
b0 "
b0 X
b11 Z
1/
#300
0/
#305
b10 [
1=
b1 _
0O
b100 G
b11 Q
b0 S
b1 Z
1/
#310
0/
#315
b111 [
0=
b0 _
b10 Z
1/
#320
0/
#325
b1 _
1^
b11 I
b1111 K
1E
b110100 "
b110100 X
b111 Z
1/
#330
0/
#335
0^
b0 I
b0 K
1M
0E
bx "
bx X
b111000 U
b1110 $
b1110 T
b11 G
1/
#340
0/
#345
b111100 U
b1111 $
b1111 T
b10 G
1/
#350
0/
#355
b1000000 U
b10000 $
b10000 T
b1 G
1/
