programms/ProfileCounter/counter.v
module counter #( parameter WIDTH = 32)
                ( input wire reset,
                             clock,
                             enable,
                             direction, /* a 1 is counting up, a 0 is counting down */
                  output reg [WIDTH-1:0] counterValue);

  always @(posedge clock)begin

    /*counterValue = (reset == 1'b1) ? {WIDTH{1'b0}} : 
                    (enable == 1'b0) ? counterValue :
                    (direction == 1'b1) ? counterValue + 1 : counterValue - 1;*/

    if (reset == 1) begin
      counterValue = {WIDTH{1'b0}};
    end else if (enable == 1) begin
      if (direction == 1) begin
        counterValue = counterValue + 1;
      end else begin
        counterValue = counterValue - 1;
      end
    end
  end
endmodule

programms/ProfileCounter/profileCi.v
module profileCi #(
    parameter [7:0] customId = 8'h00
) (
    input wire start,
    clock,
    reset,
    stall,
    busIdle,
    input wire [31:0] valueA,
    valueB,
    input wire [7:0] ciN,
    output wire done,
    output wire [31:0] result
);


  // Define enabling inputs
  //TODO: IDK if start is an impulse or a level signal

  //wire reset_0, reset_1, reset_2, reset_3;
  // Outputs
  wire [31:0] counterValue_0, counterValue_1, counterValue_2, counterValue_3;
  reg pot_0, pot_1, pot_2, pot_3;
  //wire enable_0, enable_1, enable_2, enable_3;

  wire reset_0 = (valueB[8] == 1'b1) | reset;
  wire reset_1 = (valueB[9] == 1'b1) | reset;
  wire reset_2 = (valueB[10] == 1'b1) | reset;
  wire reset_3 = (valueB[11] == 1'b1) | reset;

  reg started;
  /*always @(posedge start) begin
    
    started <= 1'b1;
  end*/

  always @(posedge clock) begin
    if (start) begin
      started = 1'b1;
    end
    
    if (reset == 1) begin
      started = 0;
      pot_0 = 0;
        pot_1 = 0;
        pot_2 = 0;
        pot_3 = 0;
    end

    //check for impulses of valueB[0-7]
    if (started || start) begin
      //check if valueB[4-7]
        if (valueB[4] == 1'b1) begin
            pot_0 = 0;
        end else if (valueB[0] == 1'b1) begin
            pot_0 = 1;
        end
        if (valueB[5] == 1'b1) begin
            pot_1 = 0;
        end else if (valueB[1] == 1'b1) begin
            pot_1 = 1;
        end
        if (valueB[6] == 1'b1) begin
            pot_2 = 0;
        end else if (valueB[2] == 1'b1) begin
            pot_2 = 1;
        end
        if (valueB[7] == 1'b1) begin
            pot_3 = 0;
        end else if (valueB[3] == 1'b1) begin
            pot_3 = 1;
        end
    end
  end

    wire enable_0 = pot_0;
    wire enable_1 = pot_1 & stall;
    wire enable_2 = pot_2 & busIdle;
    wire enable_3 = pot_3;

    // Define the direction of the counter
    
    wire direction = 1'b1;
  
  counter #(
      .WIDTH(32)
  ) counter_0 (
    .reset(reset),
      .clock(clock),
      .enable(enable_0),
      .direction(direction),
      .counterValue(counterValue_0)
  );

  counter #(
      .WIDTH(32)
  ) counter_1 (
      .reset(reset),
      .clock(clock),
      .enable(enable_1),
      .direction(direction),
      .counterValue(counterValue_1)
  );

  counter #(
      .WIDTH(32)
  ) counter_2 (
      .reset(reset),
      .clock(clock),
      .enable(enable_2),
      .direction(direction),
      .counterValue(counterValue_2)
  );

  counter #(
      .WIDTH(32)
  ) counter_3 (
      .reset(reset),
      .clock(clock),
      .enable(enable_3),
      .direction(direction),
      .counterValue(counterValue_3)
  );
  // Output we use a multiplexer to select the correct counter value to assign to result
  // The counter to be selected is based on the value of valueA[1:0] and costumGood
  // if costumGood is 0, the result is 0
  // if costumGood is 1, the result is the value of the counter selected by valueA[1:0]
  assign result = (ciN == customId && ((started == 1'b1)|| start)) ? 
                    (valueA[1:0] == 2'b00) ? counterValue_0 :
                    (valueA[1:0] == 2'b01) ? counterValue_1 :
                    (valueA[1:0] == 2'b10) ? counterValue_2 :
                    (valueA[1:0] == 2'b11) ? counterValue_3 :
                    32'b0 : 32'b0;

assign done = (ciN == customId && started == 1'b1) ? 1'b1 : 1'b0;

endmodule

programms/ProfileCounter/profileCi_tb.v

`timescale 1ps / 1ps

module proTestBench;

  // Parameters
  parameter [7:0] customId = 8'h00;

  // Signals
  reg start, clock, reset, stall, busIdle;
  reg [31:0] valueA;
  reg [31:0] valueB;
  reg [7:0] ciN;
  wire done;
  wire [31:0] result;

  // Instantiate the module
  profileCi #(
      .customId(customId)
  ) dut (
      .start(start),
      .clock(clock),
      .reset(reset),
      .stall(stall),
      .busIdle(busIdle),
      .valueA(valueA),
      .valueB(valueB),
      .ciN(ciN),
      .done(done),
      .result(result)
  );

  // Clock generation
  always #5 clock = ~clock;

  // Initial values
  initial begin
    // Initialize inputs
    start = 0;
    clock = 0;
    reset = 0;
    stall = 0;
    busIdle = 0;
    valueA = 0;
    valueB = 12'b0;
    ciN = 8'h02;

    // Apply reset
    #5
    reset = 1;
    #10 
    reset = 0;

    // Apply some test vectors
    // Set start signal and custom instruction ID
    #10
    start = 1;
    valueB = 12'b000000001111;
    #10
    start = 0;
    
    #30
    valueB = 12'b000000000000;
    stall = 1;
    busIdle = 1;
    #30
    valueA = 2'b00;
    #10
    valueA = 2'b01;
    #10
    valueA = 2'b10;
    #10
    valueA = 2'b11;
    #10
    valueA = 2'b00;
    #10
    ciN = 8'h00;
    #10
    ciN = 8'h01;


    


    // Add more test vectors as needed

    // End simulation
    $finish;
  end

  initial
    begin
      $dumpfile("ProfileSignals.vcd");
      $dumpvars(1,dut);
    end


endmodule

programms/ProfileCounter/ProfileSignals.vcd
$date
	Sat Mar 16 12:44:43 2024
$end
$version
	Icarus Verilog
$end
$timescale
	1ps
$end
$scope module proTestBench $end
$scope module dut $end
$var wire 1 ! busIdle $end
$var wire 8 " ciN [7:0] $end
$var wire 1 # clock $end
$var wire 1 $ direction $end
$var wire 1 % enable_0 $end
$var wire 1 & enable_1 $end
$var wire 1 ' enable_2 $end
$var wire 1 ( enable_3 $end
$var wire 1 ) reset $end
$var wire 1 * reset_0 $end
$var wire 1 + reset_1 $end
$var wire 1 , reset_2 $end
$var wire 1 - reset_3 $end
$var wire 1 . stall $end
$var wire 1 / start $end
$var wire 32 0 valueA [31:0] $end
$var wire 32 1 valueB [31:0] $end
$var wire 32 2 result [31:0] $end
$var wire 1 3 done $end
$var wire 32 4 counterValue_3 [31:0] $end
$var wire 32 5 counterValue_2 [31:0] $end
$var wire 32 6 counterValue_1 [31:0] $end
$var wire 32 7 counterValue_0 [31:0] $end
$var reg 1 8 pot_0 $end
$var reg 1 9 pot_1 $end
$var reg 1 : pot_2 $end
$var reg 1 ; pot_3 $end
$var reg 1 < started $end
$upscope $end
$upscope $end
$enddefinitions $end
#0
$dumpvars
x<
x;
x:
x9
x8
bx 7
bx 6
bx 5
bx 4
03
b0 2
b0 1
b0 0
0/
0.
0-
0,
0+
0*
0)
x(
0'
0&
x%
1$
0#
b10 "
0!
$end
#5
1*
1+
1,
1-
b0 7
b0 6
b0 5
b0 4
0(
0;
0:
09
0%
08
0<
1)
1#
#10
0#
#15
0*
0+
0,
0-
1#
0)
#20
0#
#25
b1 7
b1 4
1(
1;
1:
19
1%
18
1<
1#
b1111 1
1/
#30
0#
#35
b10 4
b10 7
1#
0/
#40
0#
#45
b11 7
b11 4
1#
#50
0#
#55
b100 4
b100 7
1#
#60
0#
#65
b101 7
b1 6
b1 5
b101 4
1'
1&
1#
1!
1.
b0 1
#70
0#
#75
b110 4
b10 5
b10 6
b110 7
1#
#80
0#
#85
b111 7
b11 6
b11 5
b111 4
1#
#90
0#
#95
b1000 4
b100 5
b100 6
b1000 7
1#
#100
0#
#105
b1001 7
b101 6
b101 5
b1001 4
1#
b1 0
#110
0#
#115
b1010 4
b110 5
b110 6
b1010 7
1#
b10 0
#120
0#
#125
b1011 7
b111 6
b111 5
b1011 4
1#
b11 0
#130
0#
#135
b1100 4
b1000 5
b1000 6
b1100 7
1#
b0 0
#140
0#
#145
b1101 2
13
b1101 7
b1001 6
b1001 5
b1101 4
1#
b0 "
#150
0#
#155
b0 2
03
b1110 4
b1010 5
b1010 6
b1110 7
1#
b1 "
