modules/ramDmaCi/ramDmaCi.v
//ram module adapted from course and CS-476 forum
module dualPortSSRAM #( parameter bitwidth = 32,
                        parameter nrOfEntries = 512)
                      ( input wire                             clockA, clockB,
                                                               writeEnableA, writeEnableB,
                        input wire [$clog2(nrOfEntries)-1 : 0] addressA, addressB,
                        input wire [bitwidth-1 : 0]            dataInA, dataInB,
                        output reg [bitwidth-1 : 0]            dataOutA, dataOutB);
  
  reg [bitwidth-1 : 0] memoryContent [nrOfEntries-1 : 0];
  
  always @(posedge clockA)
    begin
      if (writeEnableA == 1'b1) memoryContent[addressA] = dataInA;
      dataOutA = memoryContent[addressA];
    end

  always @(posedge clockB)
    begin
      if (writeEnableB == 1'b1) memoryContent[addressB] = dataInB;
      dataOutB = memoryContent[addressB];
    end

endmodule


module ramDmaCi #(parameter[7:0] customInstructionId = 8'h00)
                (input wire start,
                            clock,
                            reset,
                input wire [31:0]   valueA,
                                    valueB,
                input wire [7:0]    iseId,
                output wire [31:0]  result,
                output wire done);

wire s_isMyIse = (iseId == customInstructionId) ? start : 1'b0;
wire writeEnableCPU = valueA[9];
wire [8:0] addressCPU = valueA[8:0];
wire [31:0] dataOutCPU;

dualPortSSRAM #(16'd32, 16'd512 ) ram
        (.clockA(clock),
        .writeEnableA(writeEnableCPU),
        .addressA(addressCPU),
        .dataInA(valueB),
        .dataOutA(dataOutCPU));
//cpu interface

reg started;
reg finish_next_cc;

integer i;

/*always @(posedge clock)
begin
    if (reset)
    begin
        //started <= 0;
        reading <= 0;
        data_out <= 32'hFFFFFFFF;
        finish_next_cc <= 0;
        for (i = 0; i < 512; i = i + 1)
        begin
            ram[i] <= 32'hDEADBEEF;
        end
    end
    else if(s_isMyIse && start) //&& valueA[31:9] == 0)
    begin
        if (writeEnable == 1'b1)
            ram[address] = valueB;

    end
    //we "always" read
    data_out = ram[address];

    //if (almost_done == 1'b1 && (start == 1'b0 || s_isMyIse == 1'b0))
    //    almost_done <= 1'b0;
end

always @(negedge clock)
begin
    finish_next_cc = s_isMyIse & started;
end*/


assign done = (s_isMyIse & writeEnableCPU) | finish_next_cc;//(s_isMyIse == 1'b1) ? writeEnableCPU : finish_next_cc;
//we don't output the read value to result if it's a write
assign result = finish_next_cc ? dataOutCPU : 32'd0;

always @(posedge clock)
begin
  if(s_isMyIse)
  begin
    if(!writeEnableCPU)
      finish_next_cc <= 1'b1;
  end
  else
    finish_next_cc <= 1'b0;
end
endmodule

modules/ramDmaCi/tb_ramDmaCi.v
`timescale 1ps/1ps
module ramDmaCiTestBench;

/* set the time-units for simulation */



  reg reset, clock;
  initial 
    begin
      reset = 1'b1;
      clock = 1'b0;                 /* set the initial values */
      repeat (4) #5 clock = ~clock; /* generate 2 clock periods */
      reset = 1'b0;                 /* de-activate the reset */
      forever #5 clock = ~clock;    /* generate a clock with a period of 10 time-units */
    end
  
 
    reg start;
    reg [31:0] valueA;
    reg [31:0] valueB;
    reg [7:0] customId;
    reg [7:0] ciN;

    ramDmaCi #(8'h0D ) DUT
         (.clock(clock),
          .reset(reset),
          .start(start),
          .valueA(valueA),
          .valueB(valueB),
          .iseId(ciN));
  
  initial
    begin
      $dumpfile("fifoSignals.vcd"); /* define the name of the .vcd file that can be viewed by GTKWAVE */
      $dumpvars(1,DUT);             /* dump all signals inside the DUT-component in the .vcd file */
      $dumpvars(1,DUT.ram.memoryContent[0], DUT.ram.memoryContent[1], DUT.ram.memoryContent[2], DUT.ram.memoryContent[3]);
    end

  initial
    begin
        
        start <= 1'b0;
        valueA <= 32'd0;
        valueB <= 32'd0;
        @(negedge reset);            /* wait for the reset period to end */
        repeat(2) @(posedge clock);  /* wait for 2 clock cycles */

        start <= 1'b1;
        valueA <= 32'd512 | 32'd0;
        valueB <= 32'hFE;
        ciN <= 8'd13;
        repeat(1) @(posedge clock);

        valueA <= 32'd512 | 32'd1;
        valueB <= 32'h17;
        ciN <= 8'd13;
        repeat(1) @(posedge clock);

        valueA <= 32'd512 | 32'd2;
        valueB <= 32'h18;
        ciN <= 8'd13;
        repeat(1) @(posedge clock);

        valueA <= 32'd512 | 32'd3;
        valueB <= 32'h19;
        ciN <= 8'd13;
        repeat(1) @(posedge clock);

        //read
        start <= 1'b1;
        valueA <= 32'd2;
        valueB <= 32'h22;
        ciN <= 8'd13;
        repeat(1) @(posedge clock);
        start <= 1'b0;
        ciN <= 8'd0;
        repeat(1) @(posedge clock);

        start <= 1'b1;
        valueA <= 32'd1;
        valueB <= 32'h23;
        ciN <= 8'd13;
        repeat(1) @(posedge clock);
        start <= 1'b0;
        ciN <= 8'd0;
        repeat(1) @(posedge clock);
      
        start <= 1'b1;
        valueA <= 32'd3;
        valueB <= 32'h24;
        ciN <= 8'd13;
        repeat(1) @(posedge clock);
        start <= 1'b0;
        ciN <= 8'd0;
        repeat(1) @(posedge clock);

        start <= 1'b1;
        valueA <= 32'd0;
        valueB <= 32'h24;
        ciN <= 8'd13;
        repeat(1) @(posedge clock);
        start <= 1'b0;
        ciN <= 8'd0;
        repeat(1) @(posedge clock);

        repeat(2) @(posedge clock);
      $finish;                     /* finish the simulation */
    end

endmodule

modules/ramDmaCi/fifoSignals.vcd
$date
	Sat Apr 20 17:17:46 2024
$end
$version
	Icarus Verilog
$end
$timescale
	1ps
$end
$scope module ramDmaCiTestBench $end
$scope module DUT $end
$var wire 1 ! clock $end
$var wire 1 " done $end
$var wire 8 # iseId [7:0] $end
$var wire 1 $ reset $end
$var wire 1 % start $end
$var wire 32 & valueA [31:0] $end
$var wire 32 ' valueB [31:0] $end
$var wire 1 ( writeEnableCPU $end
$var wire 1 ) s_isMyIse $end
$var wire 32 * result [31:0] $end
$var wire 32 + dataOutCPU [31:0] $end
$var wire 9 , addressCPU [8:0] $end
$var parameter 8 - customInstructionId $end
$var reg 1 . finish_next_cc $end
$upscope $end
$upscope $end
$scope module ramDmaCiTestBench $end
$scope module DUT $end
$scope module ram $end
$var reg 32 / \memoryContent[0] [31:0] $end
$upscope $end
$upscope $end
$upscope $end
$scope module ramDmaCiTestBench $end
$scope module DUT $end
$scope module ram $end
$var reg 32 0 \memoryContent[1] [31:0] $end
$upscope $end
$upscope $end
$upscope $end
$scope module ramDmaCiTestBench $end
$scope module DUT $end
$scope module ram $end
$var reg 32 1 \memoryContent[2] [31:0] $end
$upscope $end
$upscope $end
$upscope $end
$scope module ramDmaCiTestBench $end
$scope module DUT $end
$scope module ram $end
$var reg 32 2 \memoryContent[3] [31:0] $end
$upscope $end
$upscope $end
$upscope $end
$enddefinitions $end
$comment Show the parameter values. $end
$dumpall
b1101 -
$end
#0
$dumpvars
bx 2
bx 1
bx 0
bx /
x.
b0 ,
bx +
bx *
0)
0(
b0 '
b0 &
0%
1$
bx #
x"
0!
$end
#5
b0 *
0"
0.
1!
#10
0!
#15
1!
#20
0$
0!
#25
1!
#30
0!
#35
1"
1(
1)
b1101 #
b11111110 '
b1000000000 &
1%
1!
#40
0!
#45
b1 ,
b10111 '
b1000000001 &
b11111110 +
b11111110 /
1!
#50
0!
#55
b10 ,
b11000 '
b1000000010 &
b10111 +
b10111 0
1!
#60
0!
#65
b11 ,
b11001 '
b1000000011 &
b11000 +
b11000 1
1!
#70
0!
#75
0"
0(
b10 ,
b100010 '
b10 &
b11001 +
b11001 2
1!
#80
0!
#85
b11000 *
1"
0)
1.
b0 #
0%
b11000 +
1!
#90
0!
#95
1)
b1 ,
b0 *
0"
b1101 #
b100011 '
b1 &
1%
0.
1!
#100
0!
#105
b10111 *
1"
0)
1.
b0 #
0%
b10111 +
1!
#110
0!
#115
1)
b11 ,
b0 *
0"
b1101 #
b100100 '
b11 &
1%
0.
1!
#120
0!
#125
b11001 *
1"
0)
1.
b0 #
0%
b11001 +
1!
#130
0!
#135
1)
b0 ,
b0 *
0"
b1101 #
b0 &
1%
0.
1!
#140
0!
#145
b11111110 *
1"
0)
1.
b0 #
0%
b11111110 +
1!
#150
0!
#155
b0 *
0"
0.
1!
